jjcli.py
jjcli-0.1.29.dist-info/entry_points.txt
jjcli-0.1.29.dist-info/WHEEL
jjcli-0.1.29.dist-info/METADATA
jjcli-0.1.29.dist-info/RECORD
