Metadata-Version: 2.1
Name: jjcli
Version: 0.1.29
Summary: # Name
Author: JJoao
Author-email: jj@di.uminho.pt
Classifier: License :: OSI Approved :: MIT License
